odoo10_addon_web_widget_float_formula-10.0.1.0.0-py2.7-nspkg.pth
odoo/addons/web_widget_float_formula/README.rst
odoo/addons/web_widget_float_formula/__init__.py
odoo/addons/web_widget_float_formula/__manifest__.py
odoo/addons/web_widget_float_formula/static/description/icon.png
odoo/addons/web_widget_float_formula/static/src/js/web_widget_float_formula.js
odoo/addons/web_widget_float_formula/static/tests/js/test_web_widget_float_formula.js
odoo/addons/web_widget_float_formula/tests/__init__.py
odoo/addons/web_widget_float_formula/tests/test_js.py
odoo/addons/web_widget_float_formula/views/web_widget_float_formula.xml
odoo10_addon_web_widget_float_formula-10.0.1.0.0.dist-info/DESCRIPTION.rst
odoo10_addon_web_widget_float_formula-10.0.1.0.0.dist-info/METADATA
odoo10_addon_web_widget_float_formula-10.0.1.0.0.dist-info/RECORD
odoo10_addon_web_widget_float_formula-10.0.1.0.0.dist-info/WHEEL
odoo10_addon_web_widget_float_formula-10.0.1.0.0.dist-info/metadata.json
odoo10_addon_web_widget_float_formula-10.0.1.0.0.dist-info/namespace_packages.txt
odoo10_addon_web_widget_float_formula-10.0.1.0.0.dist-info/top_level.txt
